LICENSE.txt
Makefile
README.txt
ez_setup.py
setup.cfg
setup.py
src/memojito/README.txt
src/memojito/__init__.py
src/memojito/tests.py
src/memojito.egg-info/PKG-INFO
src/memojito.egg-info/SOURCES.txt
src/memojito.egg-info/dependency_links.txt
src/memojito.egg-info/top_level.txt
src/memojito.egg-info/zip-safe
