Metadata-Version: 1.0
Name: memojito
Version: 0.6
Summary: simple library of memoizing decorators
Home-page: http://svn.plone.org/svn/collective/plonents/components/memojito/trunk#egg=memojito
Author: Whit Morriss
Author-email: whit@openplans.org
License: MIT
Platform: UNKNOWN
